abcFinance/__init__.py
abcFinance/account.py
abcFinance/agents.py
abcFinance/contractAPI.py
abcFinance/ledger.py
abcFinance/svg_tools.py
abcFinance-0.1.1.dist-info/LICENSE
abcFinance-0.1.1.dist-info/METADATA
abcFinance-0.1.1.dist-info/WHEEL
abcFinance-0.1.1.dist-info/top_level.txt
abcFinance-0.1.1.dist-info/zip-safe
abcFinance-0.1.1.dist-info/RECORD
