Metadata-Version: 2.1
Name: abcFinance
Version: 0.1.1
Summary: UNKNOWN
Home-page: https://github.com/AB-CE/abcFinance
License: UNKNOWN
Platform: UNKNOWN
